Metadata-Version: 2.1
Name: hack4u-drayen
Version: 1.0.0
Summary: Package example for academy
Home-page: https://hack4u.io
Author: Drayen
